README.md
setup.py
rabbitmqsimple/__init__.py
rabbitmqsimple/consumer.py
rabbitmqsimple/exception.py
rabbitmqsimple/factory.py
rabbitmqsimple/simple.py
rabbitmqsimple.egg-info/PKG-INFO
rabbitmqsimple.egg-info/SOURCES.txt
rabbitmqsimple.egg-info/dependency_links.txt
rabbitmqsimple.egg-info/requires.txt
rabbitmqsimple.egg-info/top_level.txt