Metadata-Version: 2.1
Name: rabbitmqsimple
Version: 0.4
Summary: A library to use RabbitMQ Package for multi-tenant application
Home-page: https://github.com/vcjain/rabbitmq-simple
Author: Vikash Jain
Author-email: vikash.jain@galaxyweblinks.co.in
License: MIT
Project-URL: Bug Tracker, https://github.com/vcjain/rabbitmq-simple/issues
Platform: UNKNOWN
